hc/opening_hours_js.py
hc/schulferien_org.py
hc/cli.py
hc/__main__.py
hc/yaml.py
hc/datatypes.py
hc/__init__.py
hc/_meta.py
hc/defaults.py
hc/helpers.py
hc-0.1.0.dist-info/RECORD
hc-0.1.0.dist-info/top_level.txt
hc-0.1.0.dist-info/entry_points.txt
hc-0.1.0.dist-info/metadata.json
hc-0.1.0.dist-info/DESCRIPTION.rst
hc-0.1.0.dist-info/WHEEL
hc-0.1.0.dist-info/METADATA
