Metadata-Version: 2.0
Name: hc
Version: 0.1.0
Summary: Holiday converter tool
Home-page: https://gitlab.com/ypid/hc
Author: Robin Schneider
Author-email: ypid@riseup.net
License: AGPL-3.0
Keywords: school holidays schulferien germany
Platform: UNKNOWN
Classifier: Development Status :: 3 - Alpha
Classifier: Environment :: Console
Classifier: Intended Audience :: Developers
Classifier: License :: DFSG approved
Classifier: License :: OSI Approved :: GNU Affero General Public License v3
Classifier: Natural Language :: English
Classifier: Operating System :: OS Independent
Classifier: Programming Language :: Python :: 3
Classifier: Programming Language :: Python :: 3.4
Classifier: Programming Language :: Python :: 3.5
Classifier: Programming Language :: Python :: 3.6
Classifier: Topic :: Internet :: WWW/HTTP
Classifier: Topic :: Office/Business :: Scheduling
Classifier: Topic :: Text Processing :: Markup :: HTML
Requires-Dist: ruamel.yaml
Requires-Dist: pyaml
Requires-Dist: requests-cache
Requires-Dist: xmltodict
Requires-Dist: PyQuery
Requires-Dist: appdirs
Requires-Dist: python-dateutil
Provides-Extra: test
Requires-Dist: nose; extra == 'test'
Requires-Dist: nose2; extra == 'test'
Requires-Dist: freezegun; extra == 'test'
Requires-Dist: tox; extra == 'test'
Requires-Dist: flake8; extra == 'test'
Requires-Dist: pylint; extra == 'test'
Requires-Dist: coverage; extra == 'test'
Requires-Dist: yamllint; extra == 'test'
